epl_analytics/__init__.py
epl_analytics/analysis.py
epl_analytics/cli.py
epl_analytics/core.py
epl_analytics/dashboard.py
epl_analytics/data_loader.py
epl_analytics/exporter.py
epl_analytics/visualization.py
epl_analytics-0.0.5.dist-info/METADATA
epl_analytics-0.0.5.dist-info/WHEEL
epl_analytics-0.0.5.dist-info/entry_points.txt
epl_analytics-0.0.5.dist-info/top_level.txt
epl_analytics-0.0.5.dist-info/RECORD
