Metadata-Version: 2.4
Name: epl_analytics
Version: 0.0.5
Summary: A Python package for analyzing student grades at EPL.
Author-email: Your Name <you@example.com>
License: MIT
Project-URL: Homepage, https://github.com/your-username/EPL_Analytics
Project-URL: Bug Tracker, https://github.com/your-username/EPL_Analytics/issues
Classifier: Programming Language :: Python :: 3
Classifier: License :: OSI Approved :: MIT License
Classifier: Operating System :: OS Independent
Classifier: Development Status :: 3 - Alpha
Classifier: Intended Audience :: Developers
Classifier: Intended Audience :: Education
Classifier: Intended Audience :: Science/Research
Classifier: Topic :: Scientific/Engineering :: Information Analysis
Requires-Python: >=3.8
Requires-Dist: pandas>=1.3.0
Requires-Dist: numpy>=1.21.0
Requires-Dist: matplotlib>=3.4.0
Requires-Dist: seaborn>=0.11.0
Requires-Dist: streamlit>=1.0.0
Requires-Dist: typer[all]>=0.9.0
Requires-Dist: rich>=13.0.0
